translation_new/__init__.py
translation_new/translator.py
translation_new-0.2.3.dist-info/METADATA
translation_new-0.2.3.dist-info/WHEEL
translation_new-0.2.3.dist-info/RECORD
