Metadata-Version: 2.1
Name: translation_new
Version: 0.2.3
Summary: A python package for Multi Lingual Translation using LLM
Author: Manoj Prabhakar
Author-email: manojprabhakar.isb@gmail.com
Requires-Python: >=3.10,<4.0
Classifier: Programming Language :: Python :: 3
Classifier: Programming Language :: Python :: 3.10
Classifier: Programming Language :: Python :: 3.11
Classifier: Programming Language :: Python :: 3.12
Classifier: Programming Language :: Python :: 3.13
Requires-Dist: pandas (>=2.2.3,<3.0.0)
Requires-Dist: protobuf (>=5.28.3,<6.0.0)
Requires-Dist: pytest (>=8.3.3,<9.0.0)
Requires-Dist: sentencepiece (>=0.2.0,<0.3.0)
Requires-Dist: tiktoken (>=0.8.0,<0.9.0)
Requires-Dist: torch (>=2.5.1,<3.0.0)
Requires-Dist: transformers (>=4.46.2,<5.0.0)
